vertical_multi_columns/__init__.py
vertical_multi_columns/views.py
django_vertical_multi_columns-1.0.0.dist-info/LICENSE
django_vertical_multi_columns-1.0.0.dist-info/METADATA
django_vertical_multi_columns-1.0.0.dist-info/WHEEL
django_vertical_multi_columns-1.0.0.dist-info/top_level.txt
django_vertical_multi_columns-1.0.0.dist-info/RECORD
