Metadata-Version: 2.1
Name: django-vertical-multi-columns
Version: 1.0.0
Summary: Generate content for rendering in Django templates in multiple vertically-sorted side-by-side columns
Home-page: https://github.com/swright573/django-vertical-multi-columns
Author: Susan Wright
Author-email: lsusanwright573@gmail.com
License: BSD
Project-URL: Documentation, https://django-vertical-multi-columns.readthedocs.io/en/latest/index.html
Keywords: django columns multiple vertical sorted
Platform: UNKNOWN
Classifier: Development Status :: 4 - Beta
Classifier: Environment :: Web Environment
Classifier: Intended Audience :: Developers
Classifier: License :: OSI Approved :: BSD License
Classifier: Operating System :: OS Independent
Classifier: Programming Language :: Python :: 3.7
Classifier: Programming Language :: Python :: 3.8
Classifier: Programming Language :: Python :: 3.9
Classifier: Topic :: Software Development :: Libraries :: Application Frameworks
Requires-Python: >=3.7
